[
  {
    "name": "0.9121872806373796",
    "id": "0.688088034784377",
    "url": "url://",
    "specs": "specs",
    "vendor": "vendor",
    "category": "laptop",
    "likeStatus": "no",
    "oldPrice": "200.0",
    "newPrice": "150.0",
    "sale": "15",
    "rating": "3",
    "sold": "67",
    "stock": "99"
  },
  {
    "name": "0.026920113914233768",
    "id": "0.9499185213476906",
    "url": "url://",
    "specs": "specs",
    "vendor": "vendor",
    "category": "laptop",
    "likeStatus": "no",
    "oldPrice": "200.0",
    "newPrice": "150.0",
    "sale": "15",
    "rating": "3",
    "sold": "67",
    "stock": "95"
  },
  {
    "name": "0.21530170979347196",
    "id": "0.4194095713690774",
    "url": "url://",
    "specs": "specs",
    "vendor": "vendor",
    "category": "laptop",
    "likeStatus": "no",
    "oldPrice": "200.0",
    "newPrice": "150.0",
    "sale": "15",
    "rating": "3",
    "sold": "67",
    "stock": "100"
  },
  {
    "name": "0.8243674272562422",
    "id": "0.5517279683007353",
    "url": "url://",
    "specs": "specs",
    "vendor": "vendor",
    "category": "laptop",
    "likeStatus": "no",
    "oldPrice": "200.0",
    "newPrice": "150.0",
    "sale": "15",
    "rating": "3",
    "sold": "67",
    "stock": "100"
  },
  {
    "name": "0.6661333987895193",
    "id": "0.2098077494588143",
    "url": "url://",
    "specs": "specs",
    "vendor": "vendor",
    "category": "laptop",
    "likeStatus": "no",
    "oldPrice": "200.0",
    "newPrice": "150.0",
    "sale": "15",
    "rating": "3",
    "sold": "67",
    "stock": "100"
  },
  {
    "name": "0.34421028565711864",
    "id": "0.9216760881487949",
    "url": "url://",
    "specs": "specs",
    "vendor": "vendor",
    "category": "laptop",
    "likeStatus": "no",
    "oldPrice": "200.0",
    "newPrice": "150.0",
    "sale": "15",
    "rating": "3",
    "sold": "67",
    "stock": "100"
  },
  {
    "name": "0.7320025699910551",
    "id": "0.7911923860822578",
    "url": "url://",
    "specs": "specs",
    "vendor": "vendor",
    "category": "laptop",
    "likeStatus": "no",
    "oldPrice": "200.0",
    "newPrice": "150.0",
    "sale": "15",
    "rating": "3",
    "sold": "67",
    "stock": "100"
  },
  {
    "name": "0.729621862931289",
    "id": "0.27908071621294805",
    "url": "url://",
    "specs": "specs",
    "vendor": "vendor",
    "category": "laptop",
    "likeStatus": "no",
    "oldPrice": "200.0",
    "newPrice": "150.0",
    "sale": "15",
    "rating": "3",
    "sold": "67",
    "stock": "100"
  },
  {
    "name": "0.40424644833637935",
    "id": "0.7873076385441152",
    "url": "url://",
    "specs": "specs",
    "vendor": "vendor",
    "category": "laptop",
    "likeStatus": "no",
    "oldPrice": "200.0",
    "newPrice": "150.0",
    "sale": "15",
    "rating": "3",
    "sold": "67",
    "stock": "100"
  },
  {
    "name": "0.1606395379394815",
    "id": "0.2927470978073754",
    "url": "url://",
    "specs": "specs",
    "vendor": "vendor",
    "category": "laptop",
    "likeStatus": "no",
    "oldPrice": "200.0",
    "newPrice": "150.0",
    "sale": "15",
    "rating": "3",
    "sold": "67",
    "stock": "100"
  }
]